Apper/PC.py
Apper/__init__.py
Apper-0.0.2.dist-info/LICENSE
Apper-0.0.2.dist-info/METADATA
Apper-0.0.2.dist-info/WHEEL
Apper-0.0.2.dist-info/top_level.txt
Apper-0.0.2.dist-info/RECORD
