Metadata-Version: 2.1
Name: Apper
Version: 0.0.2
Summary: !!!NEW VERSION!!! this is for create application for all opration system
Home-page: https://github.com/pypa/sampleproject
Author: parsa
Author-email: mamy4853@gmail.com
License: UNKNOWN
Platform: UNKNOWN
Classifier: Programming Language :: Python :: 3
Classifier: License :: OSI Approved :: MIT License
Classifier: Operating System :: OS Independent
